wmfwk/__init__.py
wmfwk/consume_queue.py
wmfwk/result.py
wmfwk/util/__init__.py
wmfwk/util/annotation_util.py
wmfwk/util/async_util.py
wmfwk/util/config.py
wmfwk/util/exception_util.py
wmfwk/util/genid.py
wmfwk/util/ipark_exception.py
wmfwk/util/logger.py
wmfwk/util/mail_util.py
wmfwk/util/proces_util.py
wmfwk/util/redis_util.py
wmfwk/util/rocketmq_util.py
wmfwk-1.0.1.dist-info/METADATA
wmfwk-1.0.1.dist-info/WHEEL
wmfwk-1.0.1.dist-info/top_level.txt
wmfwk-1.0.1.dist-info/RECORD
